.coveragerc
CHANGES.rst
CONTRIBUTING.rst
LICENSE.rst
MANIFEST.in
README.rst
VERSION.txt
setup.cfg
setup.py
tox.ini
OPi/GPIO.py
OPi/__init__.py
OPi/constants.py
OPi/event.py
OPi/pin_mappings.py
OPi/sysfs.py
doc/Makefile
doc/api-documentation.rst
doc/conf.py
doc/index.rst
doc/install.rst
doc/images/OrangePi_Zero_Pinout_header.jpg
doc/images/orange-pi-zero-gpio-pins-800x746.png
nanopi/__init__.py
nanopi/duo.py
nanopi/m4.py
nanopi/neocore2.py
orangepi/__init__.py
orangepi/i96.py
orangepi/lite.py
orangepi/lite2.py
orangepi/one.py
orangepi/oneplus.py
orangepi/pc.py
orangepi/pc2.py
orangepi/pcplus.py
orangepi/pi3.py
orangepi/pi3b.py
orangepi/pi4.py
orangepi/pi4B.py
orangepi/plus2e.py
orangepi/prime.py
orangepi/r1.py
orangepi/winplus.py
orangepi/zero.py
orangepi/zero2.py
orangepi/zero3.py
orangepi/zeroplus.py
orangepi/zeroplus2.py
rockpi/__init__.py
rockpi/s.py
terindo.gpio.egg-info/PKG-INFO
terindo.gpio.egg-info/SOURCES.txt
terindo.gpio.egg-info/dependency_links.txt
terindo.gpio.egg-info/not-zip-safe
terindo.gpio.egg-info/requires.txt
terindo.gpio.egg-info/top_level.txt