Metadata-Version: 2.1
Name: terindo.gpio
Version: 1.0.1
Summary: A drop-in replacement for RPi.GPIO for the Orange Pi Zero
Home-page: https://github.com/terindo/OPi.GPIO
Author: terindo
Author-email: terindo.id@gmail.com
License: MIT
Download-URL: https://github.com/terindo/OPi.GPIO/tarball/1.0.1
Keywords: orange pi opi gpio
Platform: UNKNOWN
Classifier: License :: OSI Approved :: MIT License
Classifier: Development Status :: 4 - Beta
Classifier: Intended Audience :: Education
Classifier: Intended Audience :: Developers
Classifier: Topic :: Education
Classifier: Topic :: System :: Hardware
Classifier: Topic :: System :: Hardware :: Hardware Drivers
Classifier: Programming Language :: Python :: 2
Classifier: Programming Language :: Python :: 2.7
Classifier: Programming Language :: Python :: 3
Classifier: Programming Language :: Python :: 3.4
Classifier: Programming Language :: Python :: 3.5
Classifier: Programming Language :: Python :: 3.6
Provides-Extra: docs
Provides-Extra: test
License-File: LICENSE.rst
